jupyterlab_xssguard/__init__.py
jupyterlab_xssguard/_version.py
jupyterlab_xssguard-1.0.1.data/data/share/jupyter/labextensions/jupyterlab_xssguard/package.json
jupyterlab_xssguard-1.0.1.data/data/share/jupyter/labextensions/jupyterlab_xssguard/static/323.b47943142981466b9364.js
jupyterlab_xssguard-1.0.1.data/data/share/jupyter/labextensions/jupyterlab_xssguard/static/728.32aad2d06e7f67bda55d.js
jupyterlab_xssguard-1.0.1.data/data/share/jupyter/labextensions/jupyterlab_xssguard/static/remoteEntry.4497b7fe92422cef4a20.js
jupyterlab_xssguard-1.0.1.data/data/share/jupyter/labextensions/jupyterlab_xssguard/static/style.js
jupyterlab_xssguard-1.0.1.data/data/share/jupyter/labextensions/jupyterlab_xssguard/static/third-party-licenses.json
jupyterlab_xssguard-1.0.1.data/data/share/jupyter/labextensions/jupyterlab_xssguard/install.json
jupyterlab_xssguard-1.0.1.dist-info/METADATA
jupyterlab_xssguard-1.0.1.dist-info/WHEEL
jupyterlab_xssguard-1.0.1.dist-info/licenses/LICENSE
jupyterlab_xssguard-1.0.1.dist-info/RECORD
