Metadata-Version: 2.3
Name: jupyterlab_xssguard
Version: 1.0.1
Summary: A JupyterLab extension to insert code block output into iframe.
Project-URL: Homepage, https://github.com/jfrog/jupyterlab-xssguard
Project-URL: Bug Tracker, https://github.com/jfrog/jupyterlab-xssguard/issues
Project-URL: Repository, https://github.com/jfrog/jupyterlab-xssguard.git
Author-email: Ori Hollander <orih@jfrog.com>
License:                                  Apache License
License-File: LICENSE
Keywords: jupyter,jupyterlab,jupyterlab-extension
Classifier: Framework :: Jupyter
Classifier: Framework :: Jupyter :: JupyterLab
Classifier: Framework :: Jupyter :: JupyterLab :: 4
Classifier: Framework :: Jupyter :: JupyterLab :: Extensions
Classifier: Framework :: Jupyter :: JupyterLab :: Extensions :: Prebuilt
Classifier: License :: OSI Approved :: BSD License
Classifier: Programming Language :: Python
Classifier: Programming Language :: Python :: 3
Classifier: Programming Language :: Python :: 3.8
Classifier: Programming Language :: Python :: 3.9
Classifier: Programming Language :: Python :: 3.10
Classifier: Programming Language :: Python :: 3.11
Classifier: Programming Language :: Python :: 3.12
Requires-Python: >=3.8
